torchhydro/__init__.py
torchhydro/_version.py
torchhydro/configs/__init__.py
torchhydro/configs/config.py
torchhydro/configs/model_config.py
torchhydro/datasets/__init__.py
torchhydro/datasets/data_dict.py
torchhydro/datasets/data_scalers.py
torchhydro/datasets/data_sets.py
torchhydro/datasets/data_sources.py
torchhydro/datasets/data_utils.py
torchhydro/datasets/sampler.py
torchhydro/explainers/__init__.py
torchhydro/explainers/shap.py
torchhydro/explainers/uncertainty_analysis.py
torchhydro/explainers/weight_anlysis.py
torchhydro/models/__init__.py
torchhydro/models/ann.py
torchhydro/models/crits.py
torchhydro/models/cudnnlstm.py
torchhydro/models/dpl4gr4j.py
torchhydro/models/dpl4hbv.py
torchhydro/models/dpl4xaj.py
torchhydro/models/dpl4xaj_nn4et.py
torchhydro/models/dropout.py
torchhydro/models/gnn.py
torchhydro/models/kernel_conv.py
torchhydro/models/model_dict_function.py
torchhydro/models/model_utils.py
torchhydro/models/mtslstm.py
torchhydro/models/seq2seq.py
torchhydro/models/seqforecast.py
torchhydro/models/simple_lstm.py
torchhydro/models/spplstm.py
torchhydro/trainers/__init__.py
torchhydro/trainers/deep_hydro.py
torchhydro/trainers/fabric_wrapper.py
torchhydro/trainers/resulter.py
torchhydro/trainers/train_logger.py
torchhydro/trainers/train_utils.py
torchhydro/trainers/trainer.py
torchhydro-0.1.0.dist-info/METADATA
torchhydro-0.1.0.dist-info/WHEEL
torchhydro-0.1.0.dist-info/entry_points.txt
torchhydro-0.1.0.dist-info/licenses/AUTHORS.rst
torchhydro-0.1.0.dist-info/licenses/LICENSE
torchhydro-0.1.0.dist-info/RECORD
