Metadata-Version: 2.4
Name: torchhydro
Version: 0.1.0
Summary: datasets, samplers, transforms, and pre-trained models for hydrology and water resources
Project-URL: Homepage, https://github.com/OuyangWenyu/torchhydro
Project-URL: Repository, https://github.com/OuyangWenyu/torchhydro
Project-URL: Documentation, https://github.com/OuyangWenyu/torchhydro
Project-URL: Issues, https://github.com/OuyangWenyu/torchhydro/issues
Author-email: Wenyu Ouyang <wenyuouyang@outlook.com>
License: BSD
License-File: AUTHORS.rst
License-File: LICENSE
Keywords: deep learning,hydrology,torchhydro,water resources
Classifier: Development Status :: 2 - Pre-Alpha
Classifier: Intended Audience :: Developers
Classifier: License :: OSI Approved :: BSD License
Classifier: Natural Language :: English
Classifier: Programming Language :: Python :: 3
Classifier: Programming Language :: Python :: 3.9
Classifier: Programming Language :: Python :: 3.10
Classifier: Programming Language :: Python :: 3.11
Classifier: Programming Language :: Python :: 3.12
Requires-Python: >=3.10
Requires-Dist: aqua-fetch[all]
Requires-Dist: boto3>=1.39.4
Requires-Dist: cartopy>=0.23.0
Requires-Dist: fsspec
Requires-Dist: geopandas
Requires-Dist: hydrodataset>=0.2.0
Requires-Dist: hydrodatasource>=0.2.0
Requires-Dist: hydroutils>=0.1.0
Requires-Dist: intake
Requires-Dist: kaggle
Requires-Dist: lightning>=2.5.2
Requires-Dist: minio>=7.2.15
Requires-Dist: pytest
Requires-Dist: rich>=14.0.0
Requires-Dist: s3fs>=0.4.2
Requires-Dist: scikit-learn
Requires-Dist: shap>=0.48.0
Requires-Dist: tbparse
Requires-Dist: tensorboard
Requires-Dist: torch-geometric
Requires-Dist: torch<3.0.0,>=2.0.0; sys_platform == 'darwin'
Requires-Dist: torch<3.0.0,>=2.0.0; sys_platform == 'linux'
Requires-Dist: torch<3.0.0,>=2.0.0; sys_platform == 'win32'
Requires-Dist: torchaudio>=2.0.0; sys_platform == 'darwin'
Requires-Dist: torchaudio>=2.0.0; sys_platform == 'linux'
Requires-Dist: torchaudio>=2.0.0; sys_platform == 'win32'
Requires-Dist: torchvision>=0.15.0; sys_platform == 'darwin'
Requires-Dist: torchvision>=0.15.0; sys_platform == 'linux'
Requires-Dist: torchvision>=0.15.0; sys_platform == 'win32'
Provides-Extra: dev
Requires-Dist: coverage; extra == 'dev'
Requires-Dist: flake8; extra == 'dev'
Requires-Dist: grip; extra == 'dev'
Requires-Dist: pytest-mock; extra == 'dev'
Requires-Dist: pytest-runner; extra == 'dev'
Requires-Dist: sphinx; extra == 'dev'
Requires-Dist: tox; extra == 'dev'
Requires-Dist: watchdog; extra == 'dev'
Provides-Extra: docs
Requires-Dist: aiohappyeyeballs>=2.6.1; extra == 'docs'
Requires-Dist: aiosignal>=1.4.0; extra == 'docs'
Requires-Dist: ipykernel; extra == 'docs'
Requires-Dist: ipykernel>=6.30.1; extra == 'docs'
Requires-Dist: mkdocs-git-revision-date-plugin>=0.3.2; extra == 'docs'
Requires-Dist: mkdocs-include-markdown-plugin>=1.0.0; extra == 'docs'
Requires-Dist: mkdocs-jupyter>=0.25.1; extra == 'docs'
Requires-Dist: mkdocs-material>=9.6.17; extra == 'docs'
Requires-Dist: mkdocstrings-python-legacy>=0.2.7; extra == 'docs'
Requires-Dist: mkdocstrings-python>=1.17.0; extra == 'docs'
Requires-Dist: mkdocstrings>=0.30.0; extra == 'docs'
Requires-Dist: myst-parser; extra == 'docs'
Requires-Dist: sphinx-rtd-theme; extra == 'docs'
Requires-Dist: sphinx>=4.0; extra == 'docs'
Requires-Dist: yarl>=1.20.1; extra == 'docs'
Provides-Extra: test
Requires-Dist: coverage; extra == 'test'
Requires-Dist: pytest-mock; extra == 'test'
Requires-Dist: pytest>=3; extra == 'test'
